imsp/__init__.py
imsp/imsp.py
imsp/translator.py
paddleimsp-1.0.1.dist-info/LICENSE
paddleimsp-1.0.1.dist-info/METADATA
paddleimsp-1.0.1.dist-info/WHEEL
paddleimsp-1.0.1.dist-info/top_level.txt
paddleimsp-1.0.1.dist-info/RECORD
